workflow_graph/__init__.py
workflow_graph/builder.py
workflow_graph/constants.py
workflow_graph/exceptions.py
workflow_graph/executor.py
workflow_graph/models.py
workflow_graph/utils.py
workflow_graph-0.4.2.dist-info/licenses/LICENSE
workflow_graph-0.4.2.dist-info/METADATA
workflow_graph-0.4.2.dist-info/WHEEL
workflow_graph-0.4.2.dist-info/top_level.txt
workflow_graph-0.4.2.dist-info/RECORD
