Metadata-Version: 2.4
Name: workflow-graph
Version: 0.4.2
Summary: A lightweight package for managing workflow graphs
Home-page: https://github.com/dextersjab/workflow-graph
Author: Dexter Awoyemi
Author-email: Dexter Awoyemi <dexter@dextersjab.xyz>
License-Expression: MIT
Classifier: Programming Language :: Python :: 3
Classifier: Operating System :: OS Independent
Requires-Python: >=3.9
License-File: LICENSE
Requires-Dist: typing-extensions>=4.0.0
Provides-Extra: dev
Requires-Dist: black>=25.1.0; extra == "dev"
Requires-Dist: isort>=6.0.1; extra == "dev"
Requires-Dist: flake8>=7.2.0; extra == "dev"
Requires-Dist: mypy>=1.15.0; extra == "dev"
Requires-Dist: pytest>=8.3.5; extra == "dev"
Provides-Extra: examples
Requires-Dist: pydantic>=2.0.0; extra == "examples"
Dynamic: author
Dynamic: home-page
Dynamic: license-file
